{
    "shared_item_grid": {
        "type": "array",
        "orientation": "vertical",
        "margin": "0,0",
        "content": [
            {
                "type": "array",
                "orientation": "horizontal",
                "margin": "0,0",
                "content": [
                    {
                        "type": "itemgrid",
                        "item_margin": "10, 10",
                        "h_alignment": "left",
                        "rows": [
                            [
                                "sword",
                                "shield",
                                "hook",
                                "shovel",
                                "chicken",
                                "bombs",
                                "mrHugs",
                                "nuke",
                                "lavaTrinket",
                                "burger",
                                "darkstone",
                                "boomerang",
                                "tetraGem",
                                "ending"
                            ],
                            [
                                "elder",
                                "princess",
                                "king",
                                "mimic",
                                "dragon",
                                "shopkeep",
                                "boulder",
                                "",
                                "fishingrod",
                                "whistle",
                                "anvil",
                                "strawberry",
                                "pepple",
                                "sewer"
                            ],
                            [
                                "portalMirror",
                                "vine",
                                "",
                                "button",
                                "leverLeft",
                                "leverMiddle",
                                "leverRight",
                                "",
                                "geyserVolcano",
                                "geyserWater",
                                "geyserDesert",
                                "cannonC",
                                "cannonD",
                                "cannonS",
                                "",
                                "portalFairy",
                                "statue",
                                "bus",
                                "fishingBridge",
                                "map",
                                "compass"
                            ]
                        ]
                    }
                ]
            }
        ]
    }
}